{
  "number": 23,
  "title": "Разорение",
  "description": "Избавление от старых идей и привычек, устранение непригодного, устаревшего или отжившего свой век.",
  "sections": {
    "Название": "Бо (Разорение): чистить, отделять, обрезать, обдирать, рассекать; убирать, раскрывать, оставлять без прикрытия, умалять; дойти до сути; подрезать деревья, убивать животных. Иероглиф изображает нож и знак «резьба», указывая на решительное действие ради избавления от лишнего.",
    "Образный ряд": "Неблагоприятно иметь, куда выступить.\nЭто время для избавления от непригодного и ненужного, от устаревших идей и привычек. Удаляйте внешнюю оболочку, чтобы понять суть вещей. Расчленяйте проблему и отбрасывайте несущественное. У вас должен быть четкий план и направление. Занимайтесь текущими делами. Это окончание старого цикла и подготовка к новому. Восстановите творческое равновесие, избавившись от устаревших  украшений. Проявляйте щедрость к низшим и подчиненным, чтобы упрочить собственное положение. Адаптируйтесь к переменам. Не навязывайте свою волю. Сосредоточьтесь на Символической ценности предметов и явлений, на их связи с духовным миром. Старые структуры растворяются, уступая место новому действию. Таков порядок вещей.",
    "Внешний и Внутренний миры: Гора и Земля": "Внешний предел заканчивает предыдущий цикл, в то время как новый цикл готовится на внутреннем плане.\nСкрытая возможность:  2 (Исполнение)\nИзбавление от устаревшего содержит скрытую возможность освобождения нового поля для деятельности.\nПоследовательность\nУбранство подразумевает наличие сердцевины. Осознание этого позволяет пользоваться разорением.\nОпределение\nРазорение означает избавление от лишнего.\nСимвол\nГора примыкает к земле. Разорение.\r\nЩедрость высших помогает смирить беспокойство низших.\nЛинии гексаграммы\nВначале шестерка\nУ ложа разрушены ножки.\r\nЕсли пренебречь стойкостью, будет несчастье.\nСпокойное течение жизни нарушено. Почва уходит у вас из-под ног. Измените свои взгляды, ищите поддержку в том, что вас окружает. Стойкость поможет избежать несчастья. \nШестерка вторая\nУ ложа разрушены перекладины.\r\nЕсли пренебречь стойкостью, будет несчастье.\nПроцесс разрушения продолжается, коснувшись уже несущих опор вашего бытия. Вам нужно отступить в сторону и проявить всю выдержку, какая у вас есть. Если не прислушаетесь к этому совету, путь будет закрыт.\nШестерка третья\nРазрушай это! Хулы не будет.\nПора вмешаться в разрушительный ход событий и пробиться к возможности нового созидания. Действуйте смело и решительно. Вы не пожалеете об этом.\nШестерка четвертая\nУ ложа разрушена обивка.\r\nНесчастье.\nВы зашли слишком далеко. Если вы и дальше будете отождествлять себя с силами разрушения, то причините себе большой вред. Путь закрыт, пора остановиться.\nШестерка пятая\nРыбная ловля.\r\nМилость благодаря придворной женщине.\nНичего неблагоприятного. Рыба, Символизирующая пользу и плодородие, скрыта в изменчивом потоке событий. Постарайтесь связать их воедино. Выход из ситуации будет возможен не благодаря активным действиям, а по протекции свыше. Используйте свои связи и доверьтесь воображению. Время благоприятствует вам.\nНаверху девятка\nОгромный плод не съеден.\r\nБлагородный человек обретет воз.\r\nУ ничтожного человека будет разрушено жилье.\nВы еще не в состоянии полностью осознать масштаб происходящих событий. Если вы извлекли уроки из пережитого, то сможете двигаться вперед, но если у вас не хватит мужества для откровенного самоанализа, вы останетесь у разбитого корыта. \n\n\n← 22: Убранство\n↑ к определителю\n24: Возврат →\n\n\n\n1 \n\n\n\nTweet",
    "Скрытая возможность:  2 (Исполнение)": "Избавление от устаревшего содержит скрытую возможность освобождения нового поля для деятельности.",
    "Последовательность": "Убранство подразумевает наличие сердцевины. Осознание этого позволяет пользоваться разорением.",
    "Определение": "Разорение означает избавление от лишнего.",
    "Символ": "Гора примыкает к земле. Разорение.\r\nЩедрость высших помогает смирить беспокойство низших.",
    "Линии гексаграммы": "",
    "Вначале шестерка": "У ложа разрушены ножки.\r\nЕсли пренебречь стойкостью, будет несчастье.\nСпокойное течение жизни нарушено. Почва уходит у вас из-под ног. Измените свои взгляды, ищите поддержку в том, что вас окружает. Стойкость поможет избежать несчастья.",
    "Шестерка вторая": "У ложа разрушены перекладины.\r\nЕсли пренебречь стойкостью, будет несчастье.\nПроцесс разрушения продолжается, коснувшись уже несущих опор вашего бытия. Вам нужно отступить в сторону и проявить всю выдержку, какая у вас есть. Если не прислушаетесь к этому совету, путь будет закрыт.",
    "Шестерка третья": "Разрушай это! Хулы не будет.\nПора вмешаться в разрушительный ход событий и пробиться к возможности нового созидания. Действуйте смело и решительно. Вы не пожалеете об этом.",
    "Шестерка четвертая": "У ложа разрушена обивка.\r\nНесчастье.\nВы зашли слишком далеко. Если вы и дальше будете отождествлять себя с силами разрушения, то причините себе большой вред. Путь закрыт, пора остановиться.",
    "Шестерка пятая": "Рыбная ловля.\r\nМилость благодаря придворной женщине.\nНичего неблагоприятного. Рыба, Символизирующая пользу и плодородие, скрыта в изменчивом потоке событий. Постарайтесь связать их воедино. Выход из ситуации будет возможен не благодаря активным действиям, а по протекции свыше. Используйте свои связи и доверьтесь воображению. Время благоприятствует вам.",
    "Наверху девятка": "Огромный плод не съеден.\r\nБлагородный человек обретет воз.\r\nУ ничтожного человека будет разрушено жилье.\nВы еще не в состоянии полностью осознать масштаб происходящих событий. Если вы извлекли уроки из пережитого, то сможете двигаться вперед, но если у вас не хватит мужества для откровенного самоанализа, вы останетесь у разбитого корыта."
  }
}