{
  "number": 49,
  "title": "Смена",
  "description": "Обновлять, радикально изменять; линять; отделываться от устаревшего; революция, мятеж.",
  "sections": {
    "Название": "Гэ (Смена): сдирать кожу; линять, линька; радикальная перемена, обновление; мятеж, переворот; кожа, кожаные доспехи, солдаты; устранять, отрезать, аннулировать, отменять. Иероглиф изображает шкуру животного, натянутую на раму.",
    "Образный ряд": "Если до последнего дня будешь полон правды,\r\nТо будут изначальное свершение и благоприятная стойкость.\r\nРаскаяние исчезнет.\nЭто время, когда змея сбрасывает кожу, когда радикальные перемены обновляют весь сонм вещей. Избавляйтесь от старого. Устраняйте бесполезное, чтобы очистить путь для нового. Уничтожайте то, что испортилось или пришло в упадок. Действуйте решительно и уверенно: духи благоприятствуют вам. Отриньте былые раздоры и болезненные воспоминания. Чувствуйте себя обновленным с каждым наступающим днем.Ваши сомнения и печали исчезнут. Это время, когда Небо и Земля обновляют друг друга, а люди выполняют небесные предначертания.",
    "Внешний и Внутренний миры: Водоем (Туман) и Огонь": "Изменение внутреннего осознания избавляет от, открывая новые вдохновляющие возможности.",
    "Скрытая возможность:  44 (Переченье)": "Обновление через избавление от старого содержит скрытую возможность соединения двух первичных сил.\nПоследовательность\nДао колодца не позволяет обновлять вещи. Признание этого позволяет пользоваться сменой.\nОпределение\nСмена подразумевает уход отжившего.\nСимвол\nВ центре тумана горит огонь. Смена.\r\nБлагородный человек соразмеряет ход времени со сменой времен года.\nЛинии гексаграммы\nВначале девятка\nДля укрепления перемени кожу желтой коровы.\nВы крепко связаны с прошлым и еще не можете двигаться вперед. Будьте открыты для нового импульса, когда он придет.\nШестерка вторая\nЛишь по окончании дня производи смену!\r\nПоход — к счастью. Хулы не будет.\nПришло время для перемен и обновления. Действуйте решительно. Приведите вещи в порядок. Путь открыт, ничто не препятствует вам.\nДевятка третья\nПоход — к несчастью. Стойкость ужасна.\r\nРечь трижды коснется смены у- лишь тогда к ней будет доверие.\nСейчас не время для выступления или установления дисциплины. Путь закрыт. Вы встретились с опасностью, корни которой находятся в прошлом. Подождите, пока призыв к действию не прозвучит трижды. Не упорствуйте в своих заблуждениях.\nДевятка четвертая\nВладея правдой, изменишь судьбу.\r\nСчастье. Раскаяние исчезнет.\nДействуйте без тени сомнения. Вы призваны исполнить небесное предначертание. В ситуации есть связь с духами. Время пришло, путь открыт. Все сомнения и печали исчезнут.\nДевятка пятая\nВеликий человек подвижен, как тигр.\r\nИ до гадания он уже владеет правдой.\nКогда времена меняются, великие люди преображаются вместе с ними. Они стремительно переходят от одного состояния к другому. Им не нужно оракула, чтобы понять, что делать.\nНаверху шестерка\nБлагородный человек подвижен, как барс.\r\nУ ничтожного человека меняется лицо.\r\nПоход — к несчастью.\r\nСтойкое пребывание на месте — к счастью.\nКогда времена меняются, благородный человек действует подобно барсу, но без агрессивности тигра: его поступки исполнены красоты и изящества. Ничтожный же человек может отреагировать на перемены лишь изменением лица — то есть чисто внешне. Выступление неблагоприятно. Оставайтесь там, где вы есть, и работайте над совершенствованием своих качеств. \n\n\n← 48: Колодец\n↑ к определителю\n50: Жертвенник →\n\n\n\n1 \n\n\n\nTweet",
    "Последовательность": "Дао колодца не позволяет обновлять вещи. Признание этого позволяет пользоваться сменой.",
    "Определение": "Смена подразумевает уход отжившего.",
    "Символ": "В центре тумана горит огонь. Смена.\r\nБлагородный человек соразмеряет ход времени со сменой времен года.",
    "Линии гексаграммы": "",
    "Вначале девятка": "Для укрепления перемени кожу желтой коровы.\nВы крепко связаны с прошлым и еще не можете двигаться вперед. Будьте открыты для нового импульса, когда он придет.",
    "Шестерка вторая": "Лишь по окончании дня производи смену!\r\nПоход — к счастью. Хулы не будет.\nПришло время для перемен и обновления. Действуйте решительно. Приведите вещи в порядок. Путь открыт, ничто не препятствует вам.",
    "Девятка третья": "Поход — к несчастью. Стойкость ужасна.\r\nРечь трижды коснется смены у- лишь тогда к ней будет доверие.\nСейчас не время для выступления или установления дисциплины. Путь закрыт. Вы встретились с опасностью, корни которой находятся в прошлом. Подождите, пока призыв к действию не прозвучит трижды. Не упорствуйте в своих заблуждениях.",
    "Девятка четвертая": "Владея правдой, изменишь судьбу.\r\nСчастье. Раскаяние исчезнет.\nДействуйте без тени сомнения. Вы призваны исполнить небесное предначертание. В ситуации есть связь с духами. Время пришло, путь открыт. Все сомнения и печали исчезнут.",
    "Девятка пятая": "Великий человек подвижен, как тигр.\r\nИ до гадания он уже владеет правдой.\nКогда времена меняются, великие люди преображаются вместе с ними. Они стремительно переходят от одного состояния к другому. Им не нужно оракула, чтобы понять, что делать.",
    "Наверху шестерка": "Благородный человек подвижен, как барс.\r\nУ ничтожного человека меняется лицо.\r\nПоход — к несчастью.\r\nСтойкое пребывание на месте — к счастью.\nКогда времена меняются, благородный человек действует подобно барсу, но без агрессивности тигра: его поступки исполнены красоты и изящества. Ничтожный же человек может отреагировать на перемены лишь изменением лица — то есть чисто внешне. Выступление неблагоприятно. Оставайтесь там, где вы есть, и работайте над совершенствованием своих качеств."
  }
}