{
  "number": 52,
  "title": "Сосредоточенность",
  "description": "Успокаивать, стабилизировать; предел, граница; конец цикла; становление личности.",
  "sections": {
    "Название": "Гэнъ (Сосредоточенность): предел, граница, препятствие; тихий, спокойный, неподвижный; отказ двигаться вперед; ограничивать, огораживать; заканчивать, завершать; размышлять о прошлом; прочный, твердый, простой, прямодушный; гора как внешний предел и убежище; также: останавливаться, быть остановленным. Иероглиф изображает глаз и человека, который поворачивается, желая посмотреть, что привело к нынешней ситуации.\nОбразный ряд\nСосредоточишься на своей спине,\r\nНе увидишь своего тела.\r\nПроходя по своему двору, не заметишь соседей.\r\nХулы не будет.\nГора обозначает предел, конец цикла, когда все сущее приходит к полному развитию и самовыражению. Все обретает индивидуальность. Успокойтесь и сдержите желание действовать. Обретите равновесие. Не пытайтесь наступать физически, прозревайте будущее своими чувствами и интуицией. Вы можете плыть в потоке жизни, не испытывая привязанности к вещам и не обременяя себя общественными связями. Оставайтесь там, где вы есть, и размышляйте над внутренней сутью явлений. Определите границы своих возможностей. Подгоняйте события или замедляйте их, когда требуют обстоятельства, но не запутывайтесь в мелочах.\nВнешний и Внутренний миры. Гора и Гора\nЗавершающие слова подводят итог сказанному и наводят на мысли о невысказанном.\nСкрытая возможность:  40 (Разрешение)\nОстановка и Определение предела содержат скрытую возможность освобождения от накопившегося напряжения.\nПоследовательность\nВозбуждение не длится вечно. В конце концов вещи успокаиваются. Осознание этого позволяет пользоваться сосредоточенностью.\nОпределение\nСосредоточенность означает успокоение вещей.\nСимвол\nСоединенные горы. Сосредоточенность.\r\nБлагородный человек глубоко размышляет, но не делает окончательных выводов.\nЛинии гексаграммы\nВначале шестерка\nСосредоточенность в пальцах ног.\r\nХулы не будет.\r\nБлагоприятна вечная стойкость.\nДействие останавливается, не успев начаться. Это не ошибка. Ожидание благоприятно для вас.\nШестерка вторая\nСосредоточенность в икрах.\r\nНе спасешь того, за кем следуешь.\r\nЕго сердце невесело.\nСитуация развивается, однако движение попрежнему затруднено. Вам ничто не угрожает, но вы не можете помочь близким людям.\nДевятка третья\nОстановка в бедрах. Они отходят от поясницы.\r\nУжас охватывает сердце.\nНаступает момент кризиса. Вы не можете двинуться с места и как будто разрываетесь надвое. Страх перед будущим и горькие воспоминания терзают ваше сердце. Необходимо что-то предпринять.\nШестерка четвертая\nСосредоточенность в туловище.\r\nХулы не будет.\nВы достигли определенной гармонии, успокоив противоречивые устремления. Это позволяет вам избежать неприятностей.\nШестерка пятая\nОстановка в шее.\r\nВ речах пусть будет стойкость.\r\nРаскаяние исчезнет.\nСовершенствуя навыки общения, вы исправляете ошибки, совершенные в прошлом. Ваша речь становится ясной и убедительной; печали и сомнения исчезают.\nНаверху девятка\nЗакрепи сосредоточенность.\r\nСчастье.\nЭта позиция благоприятствует щедрости, честности и великодушию. Проявляйте эти качества, и вы обнаружите их в других людях. Путь открыт. \n\n\n← 51: Возбуждение (молния)\n↑ к определителю\n53: Течение →\n\n\n\n1 \n\n\n\nTweet",
    "Образный ряд": "Сосредоточишься на своей спине,\r\nНе увидишь своего тела.\r\nПроходя по своему двору, не заметишь соседей.\r\nХулы не будет.\nГора обозначает предел, конец цикла, когда все сущее приходит к полному развитию и самовыражению. Все обретает индивидуальность. Успокойтесь и сдержите желание действовать. Обретите равновесие. Не пытайтесь наступать физически, прозревайте будущее своими чувствами и интуицией. Вы можете плыть в потоке жизни, не испытывая привязанности к вещам и не обременяя себя общественными связями. Оставайтесь там, где вы есть, и размышляйте над внутренней сутью явлений. Определите границы своих возможностей. Подгоняйте события или замедляйте их, когда требуют обстоятельства, но не запутывайтесь в мелочах.",
    "Внешний и Внутренний миры. Гора и Гора": "Завершающие слова подводят итог сказанному и наводят на мысли о невысказанном.",
    "Скрытая возможность:  40 (Разрешение)": "Остановка и Определение предела содержат скрытую возможность освобождения от накопившегося напряжения.",
    "Последовательность": "Возбуждение не длится вечно. В конце концов вещи успокаиваются. Осознание этого позволяет пользоваться сосредоточенностью.",
    "Определение": "Сосредоточенность означает успокоение вещей.",
    "Символ": "Соединенные горы. Сосредоточенность.\r\nБлагородный человек глубоко размышляет, но не делает окончательных выводов.",
    "Линии гексаграммы": "",
    "Вначале шестерка": "Сосредоточенность в пальцах ног.\r\nХулы не будет.\r\nБлагоприятна вечная стойкость.\nДействие останавливается, не успев начаться. Это не ошибка. Ожидание благоприятно для вас.",
    "Шестерка вторая": "Сосредоточенность в икрах.\r\nНе спасешь того, за кем следуешь.\r\nЕго сердце невесело.\nСитуация развивается, однако движение попрежнему затруднено. Вам ничто не угрожает, но вы не можете помочь близким людям.",
    "Девятка третья": "Остановка в бедрах. Они отходят от поясницы.\r\nУжас охватывает сердце.\nНаступает момент кризиса. Вы не можете двинуться с места и как будто разрываетесь надвое. Страх перед будущим и горькие воспоминания терзают ваше сердце. Необходимо что-то предпринять.",
    "Шестерка четвертая": "Сосредоточенность в туловище.\r\nХулы не будет.\nВы достигли определенной гармонии, успокоив противоречивые устремления. Это позволяет вам избежать неприятностей.",
    "Шестерка пятая": "Остановка в шее.\r\nВ речах пусть будет стойкость.\r\nРаскаяние исчезнет.\nСовершенствуя навыки общения, вы исправляете ошибки, совершенные в прошлом. Ваша речь становится ясной и убедительной; печали и сомнения исчезают.",
    "Наверху девятка": "Закрепи сосредоточенность.\r\nСчастье.\nЭта позиция благоприятствует щедрости, честности и великодушию. Проявляйте эти качества, и вы обнаружите их в других людях. Путь открыт."
  }
}